PythonPermission/Attribute.py
PythonPermission/Error.py
PythonPermission/__init__.py
pythonpermission-0.0.4.dist-info/METADATA
pythonpermission-0.0.4.dist-info/WHEEL
pythonpermission-0.0.4.dist-info/licenses/LICENSE
pythonpermission-0.0.4.dist-info/RECORD
