Metadata-Version: 2.1
Name: PythonPermission
Version: 0.0.4
Project-URL: Homepage, https://github.com/maxland255/PythonPermission
Project-URL: Issues, https://github.com/maxland255/PythonPermission/issues
Author-email: Maxland255 <developer@pieteraerens.eu>
License:                     GNU GENERAL PUBLIC LICENSE
License-File: LICENSE
Classifier: Development Status :: 3 - Alpha
Classifier: License :: OSI Approved :: GNU General Public License v3 (GPLv3)
Classifier: Natural Language :: English
Classifier: Operating System :: OS Independent
Classifier: Programming Language :: Python :: 3.8
Classifier: Programming Language :: Python :: 3.12
Classifier: Topic :: Security
Requires-Python: >=3.7
